README.md
setup.py
pulumi_frontegg/__init__.py
pulumi_frontegg/_inputs.py
pulumi_frontegg/_utilities.py
pulumi_frontegg/allowed_origin.py
pulumi_frontegg/get_permission.py
pulumi_frontegg/outputs.py
pulumi_frontegg/permission.py
pulumi_frontegg/permission_category.py
pulumi_frontegg/prehook.py
pulumi_frontegg/provider.py
pulumi_frontegg/pulumi-plugin.json
pulumi_frontegg/py.typed
pulumi_frontegg/redirect_uri.py
pulumi_frontegg/role.py
pulumi_frontegg/tenant.py
pulumi_frontegg/user.py
pulumi_frontegg/webhook.py
pulumi_frontegg/workspace.py
pulumi_frontegg.egg-info/PKG-INFO
pulumi_frontegg.egg-info/SOURCES.txt
pulumi_frontegg.egg-info/dependency_links.txt
pulumi_frontegg.egg-info/not-zip-safe
pulumi_frontegg.egg-info/requires.txt
pulumi_frontegg.egg-info/top_level.txt
pulumi_frontegg/config/__init__.py
pulumi_frontegg/config/vars.py