Metadata-Version: 2.1
Name: pulumi-frontegg
Version: 0.2.36
Summary: A Pulumi package for creating and managing Frontegg resources.
Home-page: https://github.com/MaterializeInc/pulumi-frontegg
License: Apache-2.0
Project-URL: Repository, https://github.com/pulumi/pulumi-frontegg
Keywords: pulumi frontegg
Platform: UNKNOWN
Requires-Python: >=3.7
